Workbook

Sheet Costing Model
B2: TechNexusGen — RFID LMS Costing Model (INTERNAL)
B4: Assumptions
B5: USD/INR rate | C5: 95.6 | D5: Source: Wise mid-market, 30 Aug 2026
B6: GST rate | C6: 0.18
B7: Package discount (INR) | C7: 34000
B8: Legend: blue/yellow cells are editable inputs — costs, sell rates, rate, GST. Everything else recalculates.
B10: # | C10: Item | D10: Specification | E10: Qty | F10: Unit | G10: Unit Cost (₹) | H10: Unit Sell (₹) | I10: Total Cost (₹) | J10: Total Sell (₹) | K10: Margin (₹) | L10: Margin %
B11: 1 | C11: UHF Self-Issue Kiosk | D11: 21.5" touchscreen, embedded UHF reader, receipt printer | E11: 1 | F11: Unit | G11: 185000 | H11: 245000 | I11: =E11*G11 -> 185000 | J11: =E11*H11 -> 245000 | K11: =J11-I11 -> 60000 | L11: =IF(J11=0,0,K11/J11) -> 0.24489796
B12: 2 | C12: UHF Self Book Return Station | D12: RFID book drop, auto check-in, security re-arm | E12: 1 | F12: Unit | G12: 125000 | H12: 165000 | I12: =E12*G12 -> 125000 | J12: =E12*H12 -> 165000 | K12: =J12-I12 -> 40000 | L12: =IF(J12=0,0,K12/J12) -> 0.24242424
B13: 3 | C13: UHF Desktop RFID Reader | D13: USB staff station reader, read/write EPC | E13: 1 | F13: PC | G13: 16000 | H13: 22000 | I13: =E13*G13 -> 16000 | J13: =E13*H13 -> 22000 | K13: =J13-I13 -> 6000 | L13: =IF(J13=0,0,K13/J13) -> 0.27272727
B14: 4 | C14: UHF RFID Book Tags | D14: Passive UHF label, 96-bit EPC + user memory | E14: 1000 | F14: PC | G14: 14 | H14: 19 | I14: =E14*G14 -> 14000 | J14: =E14*H14 -> 19000 | K14: =J14-I14 -> 5000 | L14: =IF(J14=0,0,K14/J14) -> 0.26315789
B15: 5 | C15: UHF RFID Security Gate | D15: Single corridor, 2 antenna panels, visitor counter | E15: 1 | F15: Unit | G15: 145000 | H15: 195000 | I15: =E15*G15 -> 145000 | J15: =E15*H15 -> 195000 | K15: =J15-I15 -> 50000 | L15: =IF(J15=0,0,K15/J15) -> 0.25641026
B16: 6 | C16: UHF RFID Handheld Reader | D16: Rugged Android PDA, 5 m range, shelf management app | E16: 1 | F16: PC | G16: 72000 | H16: 95000 | I16: =E16*G16 -> 72000 | J16: =E16*H16 -> 95000 | K16: =J16-I16 -> 23000 | L16: =IF(J16=0,0,K16/J16) -> 0.24210526
B17: 7 | C17: UHF RFID Member Cards | D17: PVC pre-printed long-range card | E17: 1000 | F17: PC | G17: 28 | H17: 38 | I17: =E17*G17 -> 28000 | J17: =E17*H17 -> 38000 | K17: =J17-I17 -> 10000 | L17: =IF(J17=0,0,K17/J17) -> 0.26315789
B18: 8 | C18: Library Management Software | D18: Web LMS, perpetual licence, one campus | E18: 1 | F18: Unit | G18: 110000 | H18: 165000 | I18: =E18*G18 -> 110000 | J18: =E18*H18 -> 165000 | K18: =J18-I18 -> 55000 | L18: =IF(J18=0,0,K18/J18) -> 0.33333333
B19: 9 | C19: RFID Printer (with software) | D19: Industrial thermal printer + UHF encoder | E19: 1 | F19: PC | G19: 95000 | H19: 125000 | I19: =E19*G19 -> 95000 | J19: =E19*H19 -> 125000 | K19: =J19-I19 -> 30000 | L19: =IF(J19=0,0,K19/J19) -> 0.24
B20: 10 | C20: Entrance Door/Gate (Flap Barrier) | D20: SS304 bi-directional lane, long-range reader | E20: 2 | F20: PC | G20: 115000 | H20: 150000 | I20: =E20*G20 -> 230000 | J20: =E20*H20 -> 300000 | K20: =J20-I20 -> 70000 | L20: =IF(J20=0,0,K20/J20) -> 0.23333333
B21: 11 | C21: Installation, Commissioning & Training | D21: Survey, mounting, migration, training, UAT | E21: 1 | F21: Unit | G21: 85000 | H21: 110000 | I21: =E21*G21 -> 85000 | J21: =E21*H21 -> 110000 | K21: =J21-I21 -> 25000 | L21: =IF(J21=0,0,K21/J21) -> 0.22727273
B22: 12 | C22: Shipping, Freight & Insurance | D22: Packing, road freight, transit insurance (approx) | E22: 1 | F22: Unit | G22: 45000 | H22: 55000 | I22: =E22*G22 -> 45000 | J22: =E22*H22 -> 55000 | K22: =J22-I22 -> 10000 | L22: =IF(J22=0,0,K22/J22) -> 0.18181818
C23: Sub-total | I23: =SUM(I11:I22) -> 1150000 | J23: =SUM(J11:J22) -> 1534000
C24: Less: package discount | J24: =-C7 -> -34000
C25: Net value (ex-GST) | I25: =I23 -> 1150000 | J25: =J23+J24 -> 1500000
C26: GST @ C6 | J26: =J25*C6 -> 270000
C27: Grand Total (incl. GST) | J27: =J25+J26 -> 1770000
C29: Gross margin (₹ / %) | I29: =J25-I23 -> 350000 | J29: =IF(J25=0,0,(J25-I23)/J25) -> 0.23333333

Sheet Client Quote (INR)
B2: TechNexusGen — UHF RFID Library Management System · Client Quotation (INR, ex-GST rates)
B4: # | C4: Item | D4: Qty | E4: Unit | F4: Unit Rate (₹) | G4: Amount (₹)
B5: 1 | C5: UHF Self-Issue Kiosk | D5: 1 | E5: Unit | F5: ='Costing Model'!H11 -> 245000 | G5: =D5*F5 -> 245000
B6: 2 | C6: UHF Self Book Return Station | D6: 1 | E6: Unit | F6: ='Costing Model'!H12 -> 165000 | G6: =D6*F6 -> 165000
B7: 3 | C7: UHF Desktop RFID Reader | D7: 1 | E7: PC | F7: ='Costing Model'!H13 -> 22000 | G7: =D7*F7 -> 22000
B8: 4 | C8: UHF RFID Book Tags | D8: 1000 | E8: PC | F8: ='Costing Model'!H14 -> 19 | G8: =D8*F8 -> 19000
B9: 5 | C9: UHF RFID Security Gate | D9: 1 | E9: Unit | F9: ='Costing Model'!H15 -> 195000 | G9: =D9*F9 -> 195000
B10: 6 | C10: UHF RFID Handheld Reader | D10: 1 | E10: PC | F10: ='Costing Model'!H16 -> 95000 | G10: =D10*F10 -> 95000
B11: 7 | C11: UHF RFID Member Cards | D11: 1000 | E11: PC | F11: ='Costing Model'!H17 -> 38 | G11: =D11*F11 -> 38000
B12: 8 | C12: Library Management Software | D12: 1 | E12: Unit | F12: ='Costing Model'!H18 -> 165000 | G12: =D12*F12 -> 165000
B13: 9 | C13: RFID Printer (with software) | D13: 1 | E13: PC | F13: ='Costing Model'!H19 -> 125000 | G13: =D13*F13 -> 125000
B14: 10 | C14: Entrance Door/Gate (Flap Barrier) | D14: 2 | E14: PC | F14: ='Costing Model'!H20 -> 150000 | G14: =D14*F14 -> 300000
B15: 11 | C15: Installation, Commissioning & Training | D15: 1 | E15: Unit | F15: ='Costing Model'!H21 -> 110000 | G15: =D15*F15 -> 110000
B16: 12 | C16: Shipping, Freight & Insurance | D16: 1 | E16: Unit | F16: ='Costing Model'!H22 -> 55000 | G16: =D16*F16 -> 55000
C17: Sub-total | G17: =SUM(G5:G16) -> 1534000
C18: Less: package discount | G18: =-'Costing Model'!C7 -> -34000
C19: Net value (ex-GST) | G19: =G17+G18 -> 1500000
C20: GST @ 18% | G20: =G19*'Costing Model'!C6 -> 270000
C21: Grand Total (incl. GST) | G21: =G19+G20 -> 1770000
B23: Rates pull live from the Costing Model sheet (green cells) — change sell prices there.

Sheet Client Quote (USD)
B2: TechNexusGen — UHF RFID Library Management System · Client Quotation (USD, converted at Costing Model rate)
B4: # | C4: Item | D4: Qty | E4: Unit | F4: Unit Rate ($) | G4: Amount ($)
B5: 1 | C5: UHF Self-Issue Kiosk | D5: 1 | E5: Unit | F5: =ROUND('Costing Model'!H11/'Costing Model'!$C$5,2) -> 2562.76 | G5: =D5*F5 -> 2562.76
B6: 2 | C6: UHF Self Book Return Station | D6: 1 | E6: Unit | F6: =ROUND('Costing Model'!H12/'Costing Model'!$C$5,2) -> 1725.94 | G6: =D6*F6 -> 1725.94
B7: 3 | C7: UHF Desktop RFID Reader | D7: 1 | E7: PC | F7: =ROUND('Costing Model'!H13/'Costing Model'!$C$5,2) -> 230.13 | G7: =D7*F7 -> 230.13
B8: 4 | C8: UHF RFID Book Tags | D8: 1000 | E8: PC | F8: =ROUND('Costing Model'!H14/'Costing Model'!$C$5,2) -> 0.2 | G8: =D8*F8 -> 200
B9: 5 | C9: UHF RFID Security Gate | D9: 1 | E9: Unit | F9: =ROUND('Costing Model'!H15/'Costing Model'!$C$5,2) -> 2039.75 | G9: =D9*F9 -> 2039.75
B10: 6 | C10: UHF RFID Handheld Reader | D10: 1 | E10: PC | F10: =ROUND('Costing Model'!H16/'Costing Model'!$C$5,2) -> 993.72 | G10: =D10*F10 -> 993.72
B11: 7 | C11: UHF RFID Member Cards | D11: 1000 | E11: PC | F11: =ROUND('Costing Model'!H17/'Costing Model'!$C$5,2) -> 0.4 | G11: =D11*F11 -> 400
B12: 8 | C12: Library Management Software | D12: 1 | E12: Unit | F12: =ROUND('Costing Model'!H18/'Costing Model'!$C$5,2) -> 1725.94 | G12: =D12*F12 -> 1725.94
B13: 9 | C13: RFID Printer (with software) | D13: 1 | E13: PC | F13: =ROUND('Costing Model'!H19/'Costing Model'!$C$5,2) -> 1307.53 | G13: =D13*F13 -> 1307.53
B14: 10 | C14: Entrance Door/Gate (Flap Barrier) | D14: 2 | E14: PC | F14: =ROUND('Costing Model'!H20/'Costing Model'!$C$5,2) -> 1569.04 | G14: =D14*F14 -> 3138.08
B15: 11 | C15: Installation, Commissioning & Training | D15: 1 | E15: Unit | F15: =ROUND('Costing Model'!H21/'Costing Model'!$C$5,2) -> 1150.63 | G15: =D15*F15 -> 1150.63
B16: 12 | C16: Shipping, Freight & Insurance | D16: 1 | E16: Unit | F16: =ROUND('Costing Model'!H22/'Costing Model'!$C$5,2) -> 575.31 | G16: =D16*F16 -> 575.31
C17: Sub-total | G17: =SUM(G5:G16) -> 16049.79
C18: Less: package discount | G18: =-ROUND('Costing Model'!C7/'Costing Model'!C5,0) -> -356
C19: Net value (ex-GST) | G19: =G17+G18 -> 15693.79
C20: GST @ 18% (if billed in India) | G20: =G19*'Costing Model'!C6 -> 2824.8822
C21: Grand Total (incl. GST) | G21: =G19+G20 -> 18518.672
B23: Computed live from INR rates ÷ USD/INR rate on the Costing Model sheet. The issued USD PDF (TNG-RFID-2608-01-USD, $18,526) used clean-rounded unit prices, hence a few dollars' difference.

Sheet Optional Items
B2: Optional & Phase-2 Items (ex-GST)
B4: Item | C4: Unit | D4: Rate (₹) | E4: Rate ($)
B5: Additional UHF book tags — slab rate 5,000+ pcs | C5: per 1,000 pcs | D5: 17000 | E5: =ROUND(D5/'Costing Model'!$C$5,0) -> 178
B6: Additional UHF member cards, pre-printed | C6: per 1,000 pcs | D6: 36000 | E6: =ROUND(D6/'Costing Model'!$C$5,0) -> 377
B7: Book tagging service (encode, affix, verify) on site | C7: per 1,000 books | D7: 12000 | E7: =ROUND(D7/'Costing Model'!$C$5,0) -> 126
B8: Additional RFID security gate corridor | C8: per corridor | D8: 185000 | E8: =ROUND(D8/'Costing Model'!$C$5,0) -> 1935
B9: Additional UHF self-issue kiosk | C9: per unit | D9: 240000 | E9: =ROUND(D9/'Costing Model'!$C$5,0) -> 2510
B10: Student mobile app (Android + iOS) | C10: one time | D10: 145000 | E10: =ROUND(D10/'Costing Model'!$C$5,0) -> 1517
B11: RFID smart shelf / shelf-reader bay | C11: per bay | D11: 85000 | E11: =ROUND(D11/'Costing Model'!$C$5,0) -> 889
B12: Comprehensive AMC year 2+ (hardware + software) | C12: per year | D12: 95000 | E12: =ROUND(D12/'Costing Model'!$C$5,0) -> 994
B13: LMS cloud hosting, backup & managed support | C13: per year | D13: 45000 | E13: =ROUND(D13/'Costing Model'!$C$5,0) -> 471
